Metadata-Version: 1.1
Name: bottle-utils-html
Version: 0.3.4
Summary: HTML utilities for developing apps with Bottle web framework
Home-page: http://outernet-project.github.io/bottle-utils/
Author: Outernet Inc
Author-email: branko@outernet.is
License: BSD
Keywords: bottle utils html templates
Platform: UNKNOWN
Classifier: Development Status :: 3 - Alpha
Classifier: Topic :: Utilities
Classifier: Framework :: Bottle
Classifier: Environment :: Web Environment
Classifier: License :: OSI Approved :: GNU General Public License v3 (GPLv3)
Classifier: Programming Language :: Python :: 2.7
Classifier: Programming Language :: Python :: 3.3
Classifier: Programming Language :: Python :: 3.4
